harmonized/.DS_Store
harmonized/.sync.ffs_db
harmonized/__init__.py
harmonized/chrome.py
harmonized/first.py
harmonized/hexcolor.py
harmonized/inout.py
harmonized-0.1.5.dist-info/METADATA
harmonized-0.1.5.dist-info/WHEEL
harmonized-0.1.5.dist-info/licenses/LICENSE
harmonized-0.1.5.dist-info/RECORD
