Metadata-Version: 2.1
Name: harmonized
Version: 0.1.5
Summary: Fighting for more harmony through less coding resulting in increased development speed. At least that would be nice!
Project-URL: Homepage, https://github.com/superudo3000
Project-URL: Bug Tracker, https://github.com/superudo3000
Author-email: Super Udo <superudo3000@gmail.com>
License: Copyright (c) 2018 The Python Packaging Authority
License-File: LICENSE
Classifier: License :: OSI Approved :: MIT License
Classifier: Operating System :: OS Independent
Classifier: Programming Language :: Python :: 3
Requires-Python: >=3.7
